{
	"animations": [
		{
			"loop": false,
			"offsets": [
				2,
				0
			],
			"anim": "singUP",
			"fps": 24,
			"name": "GF Dancing Beat Hair blowing CAR",
			"indices": []
		},
		{
			"loop": false,
			"offsets": [
				1,
				0
			],
			"fps": 24,
			"anim": "danceRight",
			"indices": [
				15,
				16,
				17,
				18,
				19,
				20,
				21,
				22,
				23,
				24,
				25,
				26,
				27,
				28,
				29
			],
			"name": "GF Dancing Beat Hair blowing CAR"
		},
		{
			"loop": false,
			"offsets": [
				1,
				0
			],
			"fps": 24,
			"anim": "danceLeft",
			"indices": [
				30,
				0,
				1,
				2,
				3,
				4,
				5,
				6,
				7,
				8,
				9,
				10,
				11,
				12,
				13,
				14
			],
			"name": "GF Dancing Beat Hair blowing CAR"
		}
	],
	"sarvente_floating": false,
	"healthbar_colors_middle": [
		145,
		0,
		57
	],
	"no_antialiasing": false,
	"healthbar_colors_bottom": [
		125,
		0,
		37
	],
	"image": "characters/Week4/gfCar",
	"trail_length": null,
	"trail_delay": null,
	"position": [
		0,
		0
	],
	"trail_diff": null,
	"trail_alpha": null,
	"health_drain": false,
	"healthicon": "gf",
	"shake_screen": false,
	"orbit": false,
	"drain_floor": 0.1,
	"healthbar_count": 3,
	"flip_x": false,
	"healthbar_colors": [
		165,
		0,
		77
	],
	"camera_position": [
		0,
		0
	],
	"float_magnitude": 0,
	"sing_duration": 4,
	"scare_bf": false,
	"scare_gf": false,
	"scale": 1,
	"flixel_trail": false
}